a9a/__init__.py
a9a/__main__.py
a9a/decoder.py
a9a/dir_reader.py
a9a/dir_writer.py
a9a/encoder.py
a9a-0.0.2.dist-info/METADATA
a9a-0.0.2.dist-info/WHEEL
a9a-0.0.2.dist-info/top_level.txt
a9a-0.0.2.dist-info/RECORD
