Metadata-Version: 2.1
Name: a9a
Version: 0.0.2
Summary: a9a archivator
Home-page: UNKNOWN
Author: Uladzislau Khamkou
License: UNKNOWN
Platform: UNKNOWN
Requires-Python: >=3.6
